ml_env/__init__.py
ml_env-0.1.0.dist-info/WHEEL
ml_env-0.1.0.dist-info/METADATA
ml_env-0.1.0.dist-info/RECORD
